Combinational ckts/MajorityVoter/MajorityVoter.v
module MajorityVoter(
    input a,b,c,
    output y
);
assign y = (a & b) | (a & c) | (b & c);
endmodule

Combinational ckts/MajorityVoter/MajorityVoter_tb.v
module MajorityVoter_tb;
    reg a,b,c;
    wire y;
    MajorityVoter uut(
        .a(a),
        .b(b),
        .c(c),
        .y(y)
    );
    initial begin
        $dumpfile("MajorityVoter.vcd");
        $dumpvars(0,MajorityVoter_tb);
        a = 0; b = 0; c = 0;
        #10 a = 0; b = 0; c = 1;
        #10 a = 0; b = 1; c = 0;
        #10 a = 0; b = 1; c = 1;
        #10 a = 1; b = 0; c = 0;
        #10 a = 1; b = 0; c = 1;
        #10 a = 1; b = 1; c = 0;
        #10 a = 1; b = 1; c = 1;
        #10 $finish;
    end
    endmodule

Combinational ckts/MajorityVoter/MajorityVoter.vcd
$date
	Sat Apr 26 20:32:37 2025
$end
$version
	Icarus Verilog
$end
$timescale
	1s
$end
$scope module MajorityVoter_tb $end
$var wire 1 ! y $end
$var reg 1 " a $end
$var reg 1 # b $end
$var reg 1 $ c $end
$scope module uut $end
$var wire 1 " a $end
$var wire 1 # b $end
$var wire 1 $ c $end
$var wire 1 ! y $end
$upscope $end
$upscope $end
$enddefinitions $end
#0
$dumpvars
0$
0#
0"
0!
$end
#10
1$
#20
0$
1#
#30
1!
1$
#40
0!
0$
0#
1"
#50
1!
1$
#60
0$
1#
#70
1$
