Combinational ckts/8x3Encoder/EighttoThreeEncoder.v
module EighttoThreeEncoder (
    input [7:0]a,
    output [0:2]y
);
    assign y[0] = a[4] | a[5] | a[6] | a[7];
    assign y[1] = a[2] | a[3] | a[6] | a[7];
    assign y[2] = a[1] | a[3] | a[5] | a[7];
endmodule

Combinational ckts/8x3Encoder/EighttoThreeEncoder_tb.v
module EighttoThreeEncoder_tb;
    reg [7:0]a;
    wire [0:2]y;
    EighttoThreeEncoder uut(
        .a(a),
        .y(y)
    );
    initial begin
        $dumpfile("EighttoThreeEncoder.vcd");
        $dumpvars(0,EighttoThreeEncoder_tb);
        a = 8'b00000001;
        #10 a = 8'b00000010;
        #10 a = 8'b00000100;
        #10 a = 8'b00001000;
        #10 a = 8'b00010000;
        #10 a = 8'b00100000;
        #10 a = 8'b01000000;
        #10 a = 8'b10000000;
        #10 $finish;
    end
endmodule

Combinational ckts/8x3Encoder/EighttoThreeEncoder.vcd
$date
	Sat Apr 26 16:00:05 2025
$end
$version
	Icarus Verilog
$end
$timescale
	1s
$end
$scope module EighttoThreeEncoder_tb $end
$var wire 3 ! y [0:2] $end
$var reg 8 " a [7:0] $end
$scope module uut $end
$var wire 8 # a [7:0] $end
$var wire 3 $ y [0:2] $end
$upscope $end
$upscope $end
$enddefinitions $end
#0
$dumpvars
b0 $
b1 #
b1 "
b0 !
$end
#10
b1 !
b1 $
b10 "
b10 #
#20
b10 !
b10 $
b100 "
b100 #
#30
b11 !
b11 $
b1000 "
b1000 #
#40
b100 !
b100 $
b10000 "
b10000 #
#50
b101 !
b101 $
b100000 "
b100000 #
#60
b110 !
b110 $
b1000000 "
b1000000 #
#70
b111 !
b111 $
b10000000 "
b10000000 #
