Projects/4bitALU/FourbitALU.v
module FourbitALU (
    input [3:0]a,b,
    input [2:0]s,
    output reg [3:0]result,
    output reg carryout,
    output zero,parity
);

    assign zero = (result == 4'b0000);
    assign parity = ^result;
    always @(*) begin
        case (s)
            3'b000: {carryout,result} = a + b;
            3'b001: begin
                    result = 4'b0000;
                    result = a - b;
            end
            3'b010: result = a & b;
            3'b011: result = a | b;
            3'b100: result = a ^ b;
            3'b101: result = ~a;
            3'b110: result = a + 1;
            3'b111: result = a - 1; 
            default: result = 4'b0000;
        endcase
    end
    
endmodule

Projects/4bitALU/FourbitALU_tb.v
module FourbitALU_tb;
    reg [3:0]a,b;
    reg [2:0]s;
    wire [3:0]result;
    wire carryout;
    wire parity,zero;

    FourbitALU uut(
        .a(a),
        .b(b),
        .s(s),
        .result(result),
        .carryout(carryout),
        .parity(parity),
        .zero(zero)
    );
    initial begin
        $dumpfile("FourbitALU.vcd");
        $dumpvars(0,FourbitALU_tb);
        a = 4'b0100; b = 4'b0111; s = 3'b000;
        #10 a = 4'b0100; b = 4'b0111; s = 3'b001;
        #10 a = 4'b0100; b = 4'b0111; s = 3'b010;
        #10 a = 4'b0100; b = 4'b0111; s = 3'b011;
        #10 a = 4'b0100; b = 4'b0111; s = 3'b100;
        #10 a = 4'b0100; b = 4'b0111; s = 3'b101;
        #10 a = 4'b0100; b = 4'b0111; s = 3'b110;
        #10 a = 4'b0100; b = 4'b0111; s = 3'b111;
        #10 $finish;
    end

endmodule

Projects/4bitALU/FourbitALU.vcd
$date
	Tue Apr 29 22:13:02 2025
$end
$version
	Icarus Verilog
$end
$timescale
	1s
$end
$scope module FourbitALU_tb $end
$var wire 1 ! zero $end
$var wire 4 " result [3:0] $end
$var wire 1 # parity $end
$var wire 1 $ carryout $end
$var reg 4 % a [3:0] $end
$var reg 4 & b [3:0] $end
$var reg 3 ' s [2:0] $end
$scope module uut $end
$var wire 4 ( a [3:0] $end
$var wire 4 ) b [3:0] $end
$var wire 3 * s [2:0] $end
$var wire 1 ! zero $end
$var wire 1 # parity $end
$var reg 1 $ carryout $end
$var reg 4 + result [3:0] $end
$upscope $end
$upscope $end
$enddefinitions $end
#0
$dumpvars
b1011 +
b0 *
b111 )
b100 (
b0 '
b111 &
b100 %
0$
1#
b1011 "
0!
$end
#10
0!
1#
b1101 "
b1101 +
b1 '
b1 *
#20
b100 "
b100 +
b10 '
b10 *
#30
b111 "
b111 +
b11 '
b11 *
#40
0#
b11 "
b11 +
b100 '
b100 *
#50
1#
b1011 "
b1011 +
b101 '
b101 *
#60
0#
b101 "
b101 +
b110 '
b110 *
#70
b11 "
b11 +
b111 '
b111 *
