Combinational ckts/FullSubtractor/FullSub.v
module FullSub (
    input a,b,bin,
    output d,bout
);
    assign d = a ^ b ^ bin;
    assign bout = (~a & bin) | (~a & b) | (b & bin);
endmodule

Combinational ckts/FullSubtractor/FullSub_tb.v
module FullSub_tb;
    reg a,b,bin;
    wire d,bout;
    FullSub uut(
        .a(a),
        .b(b),
        .bin(bin),
        .d(d),
        .bout(bout)
    );
    initial begin
        $dumpfile("FullSub.vcd");
        $dumpvars(0,FullSub_tb);
        a = 0; b = 0; bin = 0;
        #10 a = 0; b = 0; bin = 1;
        #10 a = 0; b = 1; bin = 0;
        #10 a = 0; b = 1; bin = 1;
        #10 a = 1; b = 0; bin = 0;
        #10 a = 1; b = 0; bin = 1;
        #10 a = 1; b = 1; bin = 0;
        #10 a = 1; b = 1; bin = 1;
        #10 $finish;
    end
    endmodule

Combinational ckts/FullSubtractor/FullSub.vcd
$date
	Fri Apr 25 16:35:14 2025
$end
$version
	Icarus Verilog
$end
$timescale
	1s
$end
$scope module FullSub_tb $end
$var wire 1 ! d $end
$var wire 1 " bout $end
$var reg 1 # a $end
$var reg 1 $ b $end
$var reg 1 % bin $end
$scope module uut $end
$var wire 1 # a $end
$var wire 1 $ b $end
$var wire 1 % bin $end
$var wire 1 " bout $end
$var wire 1 ! d $end
$upscope $end
$upscope $end
$enddefinitions $end
#0
$dumpvars
0%
0$
0#
0"
0!
$end
#10
1"
1!
1%
#20
0%
1$
#30
0!
1%
#40
0"
1!
0%
0$
1#
#50
0!
1%
#60
0%
1$
#70
1"
1!
1%
